torcrawl.py
modules/__init__.py
modules/checker.py
modules/crawler.py
modules/extractor.py
modules/tests/__init__.py
modules/tests/test_checker.py
modules/tests/test_crawler.py
modules/tests/test_extractor.py
res/__init__.py
res/keywords.yar
res/proxies.txt
res/user_agents.txt
torcrawl-1.34.dist-info/licenses/LICENSE
torcrawl-1.34.dist-info/METADATA
torcrawl-1.34.dist-info/WHEEL
torcrawl-1.34.dist-info/entry_points.txt
torcrawl-1.34.dist-info/top_level.txt
torcrawl-1.34.dist-info/RECORD
