Metadata-Version: 2.4
Name: torcrawl
Version: 1.34
Summary: A Python script to crawl and extract (regular or onion) webpages through TOR network.
Home-page: https://github.com/MikeMeliz/TorCrawl.py
Author: MikeMeliz
Author-email: mike@mikemeliz.com
License: GNU General Public License v3.0
Project-URL: Homepage, https://github.com/MikeMeliz/TorCrawl.py
Project-URL: Repository, https://github.com/MikeMeliz/TorCrawl.py
Project-URL: Issue Tracker, https://github.com/MikeMeliz/TorCrawl.py/issues
Keywords: osint,web-scraping,crawler,tor,onion,web-crawler,scraping,anonymous,privacy,security,data-extraction
Classifier: Development Status :: 5 - Production/Stable
Classifier: Intended Audience :: Developers
Classifier: Intended Audience :: System Administrators
Classifier: Intended Audience :: Information Technology
Classifier: Intended Audience :: Education
Classifier: Intended Audience :: Science/Research
Classifier: Intended Audience :: Other Audience
Classifier: License :: OSI Approved :: GNU General Public License v3 (GPLv3)
Classifier: Operating System :: POSIX :: Linux
Classifier: Operating System :: MacOS :: MacOS X
Classifier: Operating System :: Microsoft :: Windows
Classifier: Programming Language :: Python :: 3
Classifier: Programming Language :: Python :: 3.9
Classifier: Programming Language :: Python :: 3.10
Classifier: Programming Language :: Python :: 3.11
Classifier: Programming Language :: Python :: 3.12
Classifier: Topic :: Internet :: WWW/HTTP :: Indexing/Search
Classifier: Topic :: Security
Classifier: Topic :: Software Development :: Libraries :: Python Modules
Requires-Python: >=3.9
License-File: LICENSE
Requires-Dist: pysocks
Requires-Dist: beautifulsoup4>=4.7.1
Requires-Dist: yara-python
Requires-Dist: lxml
Dynamic: author
Dynamic: author-email
Dynamic: classifier
Dynamic: description
Dynamic: description-content-type
Dynamic: home-page
Dynamic: keywords
Dynamic: license
Dynamic: license-file
Dynamic: project-url
Dynamic: requires-dist
Dynamic: requires-python
Dynamic: summary
